{
	"class" : {
		"example" : "PeterUhnak 4/16/2016 13:57:35" },
	"instance" : {
		"connectWithView:" : "PeterUhnak 4/16/2016 13:57:35",
		"getBlockProducingPath" : "PeterUhnak 4/16/2016 13:57:35",
		"initialize" : "PeterUhnak 4/16/2016 13:57:35",
		"initializeElement:" : "PeterUhnak 4/16/2016 13:57:35",
		"lazyInitializeElement:" : "PeterUhnak 4/16/2016 13:57:35",
		"middle" : "PeterUhnak 4/16/2016 13:57:35",
		"middle:" : "PeterUhnak 4/16/2016 13:57:35",
		"removeHandle" : "PeterUhnak 4/16/2016 13:57:35",
		"setupView:" : "PeterUhnak 4/16/2016 13:57:35",
		"showHandle" : "PeterUhnak 4/16/2016 13:57:35" } }
