{
	"class" : {
		"gridSize" : "JanTuron 2/21/2016 20:41:18",
		"universalElementSize" : "JanTuron 2/21/2016 20:41:18" },
	"instance" : {
		"addAsTargetFor:" : "JanTuron 2/21/2016 20:41:18",
		"addModelElement:" : "JanTuron 2/21/2016 20:41:18",
		"buildEditorForm:" : "JanTuron 2/21/2016 20:41:18",
		"canBeTargetFor:" : "JanTuron 2/21/2016 20:41:18",
		"controllerForModelID:" : "JanTuron 2/21/2016 20:41:18",
		"createControllersFromModel" : "JanTuron 2/21/2016 20:41:18",
		"createInformationLink:" : "JanTuron 2/21/2016 20:41:18",
		"createLinksForTransKind:" : "JanTuron 2/21/2016 20:41:18",
		"drawSoI" : "JanTuron 2/21/2016 20:41:18",
		"figureAdded:" : "JanTuron 2/21/2016 20:41:18",
		"initializePalette:" : "JanTuron 2/21/2016 20:41:18",
		"layoutElements" : "JanTuron 2/21/2016 20:41:18",
		"modelClass" : "JanTuron 2/21/2016 20:41:18",
		"modelToControllerMapping" : "JanTuron 2/21/2016 20:41:18",
		"rebuild" : "JanTuron 2/21/2016 20:41:18",
		"refreshSoILabel" : "JanTuron 2/21/2016 20:41:18",
		"registerModelEvents:" : "JanTuron 2/21/2016 20:41:18",
		"scopeOfInterest" : "JanTuron 2/21/2016 20:41:18" } }
