{
	"class" : {
		 },
	"instance" : {
		"addAsTargetFor:" : "JanTuron 1/14/2016 10:47:07",
		"addModelElement:" : "JanTuron 1/14/2016 10:47:07",
		"addTranslationCallback:" : "JanTuron 1/14/2016 10:47:07",
		"canBeTargetFor:" : "JanTuron 1/14/2016 10:47:07",
		"createControllers" : "JanTuron 1/14/2016 10:47:07",
		"createLinksForTransKind:" : "JanTuron 1/14/2016 10:47:07",
		"drawSoI" : "JanTuron 1/14/2016 10:47:07",
		"figureAdded:" : "JanTuron 1/14/2016 10:47:07",
		"initializePalette:" : "JanTuron 1/14/2016 10:47:07",
		"layoutFigures:" : "JanTuron 1/14/2016 10:47:07",
		"modelClass" : "JanTuron 1/14/2016 10:47:07",
		"modelToControllerMapping" : "JanTuron 1/14/2016 10:47:07",
		"rebuild" : "JanTuron 1/14/2016 10:47:07",
		"scopeOfInterest" : "JanTuron 1/14/2016 10:47:07" } }
