{
	"class" : {
		 },
	"instance" : {
		"add:" : "JanTuron 1/12/2016 15:54:58",
		"addInitiationLink:" : "JanTuron 1/12/2016 15:54:58",
		"addWaitingLink:" : "JanTuron 1/12/2016 15:54:58",
		"codeName" : "JanTuron 1/12/2016 15:54:58",
		"correspondingProductKind" : "JanTuron 1/12/2016 15:54:58",
		"correspondingProductKind:" : "JanTuron 1/12/2016 15:54:58",
		"correspondingProductKinds" : "JanTuron 1/12/2016 15:54:58",
		"createInitiationLinkTo:" : "JanTuron 1/12/2016 15:54:58",
		"executorRole" : "JanTuron 1/12/2016 15:54:58",
		"executorRole:" : "JanTuron 1/12/2016 15:54:58",
		"initialize" : "JanTuron 1/12/2016 15:54:58",
		"initiationLinks" : "JanTuron 1/12/2016 15:54:58",
		"initiatorRole" : "JanTuron 1/12/2016 15:54:58",
		"initiatorRole:" : "JanTuron 1/12/2016 15:54:58",
		"ocdPosition" : "JanTuron 1/12/2016 15:54:58",
		"ocdPosition:" : "JanTuron 1/12/2016 15:54:58",
		"psdPosition" : "JanTuron 1/12/2016 15:54:58",
		"psdPosition:" : "JanTuron 1/12/2016 15:54:58",
		"waitingLinks" : "JanTuron 1/12/2016 15:54:58" } }
